.editorconfig
.gitignore
.gitlab-ci.yml
LICENSE
README.rst
publish.settings.sh
publish.sh
pyproject.toml
.idea/modules.xml
.idea/peek-logic-service.iml
.idea/inspectionProfiles/Project_Default.xml
.idea/inspectionProfiles/profiles_settings.xml
peek_logic_service/PeekServerConfig.py
peek_logic_service/PlatformDependencyTest.py
peek_logic_service/__init__.py
peek_logic_service/alembic.ini
peek_logic_service/run_peek_logic_service.py
peek_logic_service/run_peek_logic_service_build_only.py
peek_logic_service/run_peek_logic_service_migrate_only.py
peek_logic_service/winsvc_peek_server.py
peek_logic_service.egg-info/PKG-INFO
peek_logic_service.egg-info/SOURCES.txt
peek_logic_service.egg-info/dependency_links.txt
peek_logic_service.egg-info/entry_points.txt
peek_logic_service.egg-info/requires.txt
peek_logic_service.egg-info/top_level.txt
peek_logic_service/alembic/env.py
peek_logic_service/alembic/script.py.mako
peek_logic_service/alembic/versions/05cf60a0fd22_initial_setup.py
peek_logic_service/alembic/versions/3aa82a9abe67_enabled_postgis.py
peek_logic_service/alembic/versions/5ad8b58df646_create.py
peek_logic_service/alembic/versions/7923ec94177a_added_peek_environent_tables.py
peek_logic_service/alembic/versions/__init__.py
peek_logic_service/alembic/versions/bc1622f6c16c_added_file_dir_name_to_peekappinfo.py
peek_logic_service/alembic/versions/c2a3b93e178d_added_mssql_csvtotable.py
peek_logic_service/alembic/versions/c5e78990adf6_added_initial_tables.py
peek_logic_service/backend/AdminSiteResource.py
peek_logic_service/backend/__init__.py
peek_logic_service/backend/auth/AdminAuthChecker.py
peek_logic_service/backend/auth/AdminAuthElement.py
peek_logic_service/backend/auth/AdminAuthRealm.py
peek_logic_service/backend/auth/AdminAuthResource.py
peek_logic_service/backend/auth/AdminAuthTemplate.xml
peek_logic_service/backend/auth/AdminUserAccess.py
peek_logic_service/backend/auth/__init__.py
peek_logic_service/backend/dashboard/PeekAdmDashboardListHandler.py
peek_logic_service/backend/dashboard/__init__.py
peek_logic_service/backend/environment/PeekAdmEnvHandler.py
peek_logic_service/backend/environment/__init__.py
peek_logic_service/backend/navbar/PeekAdmNavbarHandler.py
