Metadata-Version: 2.4
Name: peek-logic-service
Version: 5.1.2
Summary: Peek Logic Service - where Peek Logic App is served
Author-email: Synerty <contact@synerty.com>
Project-URL: Homepage, https://github.com/Synerty/peek-logic-service
Keywords: Peek,Python,Platform,synerty
License-File: LICENSE
Requires-Dist: peek-plugin-base==5.1.2
Requires-Dist: peek-platform==5.1.2
Requires-Dist: peek-admin-app==5.1.2
Requires-Dist: peek-admin-doc==5.1.2
Dynamic: license-file
